Metadata-Version: 2.1
Name: p3s9
Version: 0.0.0.1
Summary: -
Home-page: UNKNOWN
Author: pYSjI
Author-email: yangdaz3@gmail.com
License: UNKNOWN
Platform: UNKNOWN
Requires-Python: >=3.6
Requires-Dist: pandas
Requires-Dist: requests
